cec_clustering/__init__.py
cec_clustering/cec.py
cec_clustering-0.1.dist-info/DESCRIPTION.rst
cec_clustering-0.1.dist-info/METADATA
cec_clustering-0.1.dist-info/RECORD
cec_clustering-0.1.dist-info/WHEEL
cec_clustering-0.1.dist-info/metadata.json
cec_clustering-0.1.dist-info/top_level.txt
