Metadata-Version: 2.0
Name: cec-clustering
Version: 0.1
Summary: Cross entropy clustering algorithm
Home-page: https://github.com/paulinapmk/cec_clustering
Author: Paulina Kania
Author-email: info@paulinakania.pl
License: MIT
Platform: UNKNOWN
